README.md
setup.py
autogpy/__init__.py
autogpy/autognuplot.py
autogpy/autognuplot_terms.py
autogpy/plot_helpers.py
autogpy.egg-info/PKG-INFO
autogpy.egg-info/SOURCES.txt
autogpy.egg-info/dependency_links.txt
autogpy.egg-info/requires.txt
autogpy.egg-info/top_level.txt