Metadata-Version: 2.1
Name: autogpy
Version: 0.2
Summary: autogpy: AutoGnuplot.py - automatic generation of gnuplot figures (including script and data) from python
Home-page: https://github.com/acorbe/autogpy
Author: Alessandro Corbetta
Author-email: a.corbetta@tue.nl
License: new BSD
Platform: UNKNOWN
